Verilog_Practice_Programs_VivadoProject/Verilog_Practice_Programs_VivadoProject.srcs/sources_1/new/counter_3bit_up.v
`timescale 1ns / 1ps
//////////////////////////////////////////////////////////////////////////////////
// Company: 
// Engineer: Supantha Sen
// 
// Create Date: 15.06.2024 12:36:39
// Design Name: 3-bit Up Counter
// Module Name: counter_3bit_up
// Project Name: Verilog Practice Programs
// Target Devices: 
// Tool Versions: 
// Description: 
// 
// Dependencies: 
// 
// Revision:
// Revision 0.01 - File Created
// Additional Comments:
// 
//////////////////////////////////////////////////////////////////////////////////


module counter_3bit_up(
    input clk,
    input rst,
    input en,
    output [2:0] count
    );

    reg [2:0] count;

    always @ (posedge clk) begin
        if (rst) begin
            count <= 3'b000;
        end
        else if (en) begin
            count <= count + 1;
        end
    end    

endmodule

Verilog_Practice_Programs_VivadoProject/Verilog_Practice_Programs_VivadoProject.srcs/sim_1/imports/new/tb_counter_3bit_up.v
`timescale 1ns / 1ps
//////////////////////////////////////////////////////////////////////////////////
// Company: 
// Engineer: 
// 
// Create Date: 15.06.2024 12:45:34
// Design Name: 
// Module Name: tb_counter_3bit_up
// Project Name: 
// Target Devices: 
// Tool Versions: 
// Description: 
// 
// Dependencies: 
// 
// Revision:
// Revision 0.01 - File Created
// Additional Comments:
// 
//////////////////////////////////////////////////////////////////////////////////


module tb_counter_3bit_up();

    reg clk, en, rst;
    wire [2:0] count;

    counter_3bit_up U0 (
                    .clk(clk),
                    .rst(rst),
                    .en(en),
                    .count(count)
                );

    always begin
        #10 clk = !clk;
    end
    
    initial begin
        $dumpvars;
        clk = 0;
        en = 0; 
        rst = 1;

        #25
        en = 1;
        
        #2
        rst = 0;

        #200
        en = 0;
        
        #100
        en = 1;
                                                                                                                

        #500 $finish;
    end
    
endmodule

Verilog_Practice_Programs_VivadoProject/Verilog_Practice_Programs_VivadoProject.sim/sim_1/behav/xsim/dump.vcd
$date
   Sat Jun 15 12:48:14 2024
$end

$version
  2024.1
$end

$timescale
  1ps
$end

$scope module tb_counter_3bit_up $end
$var reg 1 ! clk $end
$var reg 1 " en $end
$var reg 1 # rst $end
$var wire 3 $ count [2:0] $end
$scope module U0 $end
$var wire 1 % clk $end
$var wire 1 & rst $end
$var wire 1 ' en $end
$var reg 3 ( count [2:0] $end
$upscope $end
$upscope $end
$enddefinitions $end

#0
$dumpvars
0!
0"
1#
bx $
0%
1&
0'
bx (
$end

#10000
1!
b0 $
1%
b0 (

#20000
0!
0%

#25000
1"
1'

#27000
0#
0&

#30000
1!
b1 $
1%
b1 (

#40000
0!
0%

#50000
1!
b10 $
1%
b10 (

#60000
0!
0%

#70000
1!
b11 $
1%
b11 (

#80000
0!
0%

#90000
1!
b100 $
1%
b100 (

#100000
0!
0%

#110000
1!
b101 $
1%
b101 (

#120000
0!
0%

#130000
1!
b110 $
1%
b110 (

#140000
0!
0%

#150000
1!
b111 $
1%
b111 (

#160000
0!
0%

#170000
1!
b0 $
1%
b0 (

#180000
0!
0%

#190000
1!
b1 $
1%
b1 (

#200000
0!
0%

#210000
1!
b10 $
1%
b10 (

#220000
0!
0%

#227000
0"
0'

#230000
1!
1%

#240000
0!
0%

#250000
1!
1%

#260000
0!
0%

#270000
1!
1%

#280000
0!
0%

#290000
1!
1%

#300000
0!
0%

#310000
1!
1%

#320000
0!
0%

#327000
1"
1'

#330000
1!
b11 $
1%
b11 (

#340000
0!
0%

#350000
1!
b100 $
1%
b100 (

#360000
0!
0%

#370000
1!
b101 $
1%
b101 (

#380000
0!
0%

#390000
1!
b110 $
1%
b110 (

#400000
0!
0%

#410000
1!
b111 $
1%
b111 (

#420000
0!
0%

#430000
1!
b0 $
1%
b0 (

#440000
0!
0%

#450000
1!
b1 $
1%
b1 (

#460000
0!
0%

#470000
1!
b10 $
1%
b10 (

#480000
0!
0%

#490000
1!
b11 $
1%
b11 (

#500000
0!
0%

#510000
1!
b100 $
1%
b100 (

#520000
0!
0%

#530000
1!
b101 $
1%
b101 (

#540000
0!
0%

#550000
1!
b110 $
1%
b110 (

#560000
0!
0%

#570000
1!
b111 $
1%
b111 (

#580000
0!
0%

#590000
1!
b0 $
1%
b0 (

#600000
0!
0%

#610000
1!
b1 $
1%
b1 (

#620000
0!
0%

#630000
1!
b10 $
1%
b10 (

#640000
0!
0%

#650000
1!
b11 $
1%
b11 (

#660000
0!
0%

#670000
1!
b100 $
1%
b100 (

#680000
0!
0%

#690000
1!
b101 $
1%
b101 (

#700000
0!
0%

#710000
1!
b110 $
1%
b110 (

#720000
0!
0%

#730000
1!
b111 $
1%
b111 (

#740000
0!
0%

#750000
1!
b0 $
1%
b0 (

#760000
0!
0%

#770000
1!
b1 $
1%
b1 (

#780000
0!
0%

#790000
1!
b10 $
1%
b10 (

#800000
0!
0%

#810000
1!
b11 $
1%
b11 (

